{

"含义": "指植物新生出的幼嫩部分,如嫩叶、嫩枝等",
"字形": "芽（一个「艸」字加一个「牙」字）",
"读音": "yá",
"字源": "从艸牙。艸指草木,牙表示新生的嫩芽。合起来就是指植物新生出的幼嫩部分。",
"常用词组": [
"嫩芽",
"萌芽",
"茶芽",
"花芽",
"芽苗"
],
"成语": [
"萌芽初露",
"欣欣向荣",
"春回大地",
"笑靥如花",
"百花争艳"
],
"例句": {
"春天来了,园子里的嫩芽悄悄冒了出来。",
"经过休眠期,这棵植物的新芽终于萌发了。",
"采摘茶园里的嫩芽制作出了上品绿茶。",
"樱花树上的花芽正逐渐绽放,很快就会开放了。",
"我们在屋前栽种了一些芽苗,希望它们能健康成长。"
},
"短故事": [
"据说,在古代有一位诗人独自漫步在林间,突然发现一株植物的幼芽正缓缓冒出地面。他长久驻足观赏,感受到大自然生命力的复苏,内心也为之欢欣鼓舞。后来在诗中写下"春回大地,萌芽初露"的诗句,表达了对大自然复兴的喜悦。这段故事说明了芽的象征意义。",
"在中国文化传统中,芽常被视为生机勃勃的代表。有一幅古典画作描绘了一束欣欣向荣的茶芽,画面中的芽看起来充满生命力,展现了大自然生长的意象。这种充满朝气的景象往往被用来比喻那些积极进取、充满活力的人或事物。"
],
"诗词": [
}